{
  "id": "gov_ibsrela_title_purple_only",
  "brand_id": "ibsrela",
  "gov_type": "mlr_claim",
  "subject": "Title/first line is purple; no other text in the email may be purple",
  "match": {
    "method": "semantic"
  },
  "verdict": "requires_qualifier",
  "severity": "warn",
  "rationale": "Title is how the email starts and should always be purple; the first line should always be purple; no other text in the email can be purple colored.",
  "content_types": [
    "email"
  ],
  "status": "active",
  "version": 1
}