[
  {
    "entity_id": "tok_lisraya_icon_callout_left_padding_formula",
    "field": "",
    "schema_version": "2.0",
    "spans": [
      {
        "doc_ref": "color_scheme_rules[6]",
        "end": 869,
        "match": "exact",
        "quote": "(? `W/2 + 24px`)",
        "start": 853,
        "unit_ids": [
          "u_color_scheme_rules_6_0008"
        ]
      },
      {
        "doc_ref": "color_scheme_rules[6]",
        "end": 5552,
        "match": "exact",
        "quote": "**box left-padding = `W/2 + 24px`**",
        "start": 5517,
        "unit_ids": [
          "u_color_scheme_rules_6_0047"
        ]
      }
    ],
    "value_check": {
      "detail": null,
      "status": "n/a"
    },
    "verification": "span_verified"
  },
  {
    "entity_id": "tok_lisraya_icon_callout_left_padding_formula",
    "field": "value.default",
    "schema_version": "2.0",
    "spans": [
      {
        "doc_ref": "color_scheme_rules[6]",
        "end": 869,
        "match": "exact",
        "quote": "the **left padding must clear the overhanging badge half plus a gap** (? `W/2 + 24px`)",
        "start": 783,
        "unit_ids": [
          "u_color_scheme_rules_6_0008"
        ]
      }
    ],
    "value_check": {
      "detail": null,
      "status": "n/a"
    },
    "verification": "unverified"
  }
]
