[
  {
    "entity_id": "tok_lisraya_secondary_body_type",
    "field": "",
    "schema_version": "2.0",
    "spans": [
      {
        "doc_ref": "content_pattern_rules[1]",
        "end": 1399,
        "match": "exact",
        "quote": "Secondary/supporting body: 14px / 21px (150%), Nunito Sans Regular — use sparingly",
        "start": 1317,
        "unit_ids": [
          "u_content_pattern_rules_1_0016"
        ]
      }
    ],
    "value_check": {
      "detail": null,
      "status": "n/a"
    },
    "verification": "span_verified"
  },
  {
    "entity_id": "tok_lisraya_secondary_body_type",
    "field": "value.default",
    "schema_version": "2.0",
    "spans": [
      {
        "doc_ref": "content_pattern_rules[1]",
        "end": 1383,
        "match": "exact",
        "quote": "Secondary/supporting body: 14px / 21px (150%), Nunito Sans Regular",
        "start": 1317,
        "unit_ids": [
          "u_content_pattern_rules_1_0016"
        ]
      }
    ],
    "value_check": {
      "detail": null,
      "status": "n/a"
    },
    "verification": "unverified"
  }
]
