[
  {
    "entity_id": "tok_lisraya_font_family_agenda",
    "field": "",
    "schema_version": "2.0",
    "spans": [
      {
        "doc_ref": "internal_banner_rules[0]",
        "end": 221,
        "match": "exact",
        "quote": "Agenda, is the primary headline font",
        "start": 185,
        "unit_ids": [
          "u_internal_banner_rules_0_0003"
        ]
      }
    ],
    "value_check": {
      "detail": null,
      "status": "n/a"
    },
    "verification": "span_verified"
  },
  {
    "entity_id": "tok_lisraya_font_family_agenda",
    "field": "value.default",
    "schema_version": "2.0",
    "spans": [
      {
        "doc_ref": "content_pattern_rules[1]",
        "end": 180,
        "match": "exact",
        "quote": "**Agenda** (Adobe font)",
        "start": 157,
        "unit_ids": [
          "u_content_pattern_rules_1_0003"
        ]
      }
    ],
    "value_check": {
      "detail": "matched 'agenda'",
      "status": "pass"
    },
    "verification": "value_verified"
  }
]
