[
  {
    "entity_id": "tok_lisraya_icon_callout_section_padding",
    "field": "",
    "schema_version": "2.0",
    "spans": [
      {
        "doc_ref": "color_scheme_rules[6]",
        "end": 2841,
        "match": "exact",
        "quote": "padding=\"16px 25px\"",
        "start": 2822,
        "unit_ids": [
          "u_color_scheme_rules_6_0036"
        ]
      }
    ],
    "value_check": {
      "detail": null,
      "status": "n/a"
    },
    "verification": "span_verified"
  },
  {
    "entity_id": "tok_lisraya_icon_callout_section_padding",
    "field": "value.default",
    "schema_version": "2.0",
    "spans": [
      {
        "doc_ref": "color_scheme_rules[6]",
        "end": 2842,
        "match": "exact",
        "quote": "<mj-section background-color=\"#ffffff\" padding=\"16px 25px\">",
        "start": 2783,
        "unit_ids": [
          "u_color_scheme_rules_6_0036"
        ]
      }
    ],
    "value_check": {
      "detail": null,
      "status": "n/a"
    },
    "verification": "unverified"
  }
]
