[
  {
    "entity_id": "tok_lisraya_type_scale_icon_callout_text",
    "field": "",
    "schema_version": "2.0",
    "spans": [
      {
        "doc_ref": "color_scheme_rules[6]",
        "end": 954,
        "match": "exact",
        "quote": "Nunito Sans weight 800, ~21px / 28px line-height",
        "start": 906,
        "unit_ids": [
          "u_color_scheme_rules_6_0009"
        ]
      }
    ],
    "value_check": {
      "detail": null,
      "status": "n/a"
    },
    "verification": "span_verified"
  },
  {
    "entity_id": "tok_lisraya_type_scale_icon_callout_text",
    "field": "value.default",
    "schema_version": "2.0",
    "spans": [
      {
        "doc_ref": "color_scheme_rules[6]",
        "end": 1044,
        "match": "failed",
        "quote": "~21px / 28px line-height",
        "start": 871,
        "unit_ids": [
          "u_color_scheme_rules_6_0009"
        ]
      }
    ],
    "value_check": {
      "detail": "normalized \"{'font_size':_'21px',_'line_height':_'28px',_'weight':_'800'}\" not found in cited units or neighbors",
      "status": "fail"
    },
    "verification": "unverified"
  }
]
