{
  "id": "tok_lisraya_radius_accent_large_email",
  "brand_id": "lisraya",
  "token_type": "radius",
  "kind": "primitive",
  "key": "radius.accent_shape.large_email",
  "value": {
    "default": "120px & 6px",
    "default_evidence": {
      "quotes": [
        "large: 120px & 6px"
      ],
      "unit_ids": [
        "u_design_pattern_rules_3_0003"
      ]
    },
    "variants": null
  },
  "aliases": [
    "large accent radius email",
    "radius.accent_shape.email_large"
  ],
  "scope": "global",
  "notes": "Email px conversion at 96dpi for large accent shape.",
  "status": "active",
  "version": 1
}