{
  "id": "rule_lisraya_moa_statements_verbatim",
  "brand_id": "lisraya",
  "rule_class": "copy_editorial",
  "audience": "dtp_patient",
  "scope": "campaign",
  "selector": {},
  "evaluation_scope": "section",
  "constraint_type": "verbatim_content",
  "effect": {
    "content": "Primary: \"Unlike other treatments for dermatomyositis (DM), which suppress the immune system generally, LISRAYA targets the root cause of the disease.\" Alternate: \"...LISRAYA works by turning off the specific inflammatory switches that are stuck in the 'on' position.\"",
    "governance_id": "gov_lisraya_moa_primary",
    "trigger": null
  },
  "polarity": "must",
  "hardness": "hard_constraint",
  "precedence": 0,
  "token_ids": [],
  "asset_ids": [],
  "governance_ids": [
    "gov_lisraya_dm_abbreviation",
    "gov_lisraya_moa_alt",
    "gov_lisraya_moa_primary"
  ],
  "rule_text": "The mechanism-of-action language must be used verbatim. Primary: \"Unlike other treatments for dermatomyositis (DM), which suppress the immune system generally, LISRAYA targets the root cause of the disease.\" Alternate: \"...LISRAYA works by turning off the specific inflammatory switches that are stuck in the 'on' position.\"",
  "intent": "Lock approved MOA claims exactly as reviewed.",
  "source": "design_bible",
  "doc_ref": "content_pattern_rules[7]",
  "group_id": "grp_lisraya_content_pattern_rules_07",
  "status": "active",
  "version": 1,
  "summary": "Use verbatim mechanism-of-action text: primary \"Unlike other treatments for dermatomyositis (DM), which suppress immune system generally, LISRAYA targets root cause.\" Alternate: \"LISRAYA works by turning off specific inflammatory switches stuck 'on'."
}