{
  "id": "tpl_lisraya_icon_callout_box",
  "brand_id": "lisraya",
  "name": "Icon Callout Box Section",
  "description": "Light-blue accent-shape box with a short blue headline and a white icon badge straddling the box's left edge (50/50 over blue and page background). Used for supporting proof-point statements. Includes Outlook degrade caveats.",
  "source": "design_bible",
  "file": "templates/tpl_lisraya_icon_callout_box.mjml",
  "instance_of": "sub_lisraya_email_primary_1col",
  "fills_section_types": [
    "callout"
  ],
  "usage_conditions": {
    "requires_content_tags": [],
    "forbidden_content_tags": []
  },
  "notes": "Outlook (Word engine) ignores position:absolute \u2014 badge drops to top-left flush inner edge. Brand-safe option: pre-composite badge as transparent PNG or bake into box background image with live text. Every other rule stays identical.",
  "status": "active",
  "version": 1
}