{
  "id": "tok_ibsrela_color_periwinkle",
  "brand_id": "ibsrela",
  "token_type": "color",
  "kind": "primitive",
  "key": "color.campaign.periwinkle",
  "value": {
    "default": "#7B7BED",
    "variants": null
  },
  "aliases": [
    "Periwinkle",
    "PMS 2125"
  ],
  "tier": "campaign",
  "scope": "campaign:flip_the_script",
  "usage_ratio": 0.33,
  "notes": "Flip The Script campaign color; RGB 123/123/237; paired scene Office; never periwinkle text on white; also a dark-group CTA background (Cake_lockup)",
  "status": "active",
  "version": 1
}