{
  "id": "rule_ibsrela_symptom_trio_icon_styling",
  "brand_id": "ibsrela",
  "rule_class": "iconography",
  "tags": [
    "color_application",
    "typography"
  ],
  "audience": "dtp_patient",
  "scope": "brand",
  "selector": {
    "section_types": [
      "symptom_trio"
    ]
  },
  "evaluation_scope": "section",
  "constraint_type": "binding",
  "effect": {
    "assignments": [
      {
        "element_path": "symptom_trio.icon.label",
        "token_id": "tok_ibsrela_color_dark_blue"
      }
    ]
  },
  "polarity": "must",
  "hardness": "hard_constraint",
  "precedence": 0,
  "token_ids": [
    "tok_ibsrela_color_dark_blue"
  ],
  "asset_ids": [],
  "governance_ids": [],
  "rule_text": "Each symptom icon is a circular green-tinted icon with the symptom label beneath it set in navy #262262 (tok_ibsrela_color_dark_blue).",
  "intent": "Lock the visual treatment of the symptom trio icons and labels.",
  "source": "design_bible",
  "doc_ref": "design_pattern_rules[3]",
  "group_id": "grp_ibsrela_design_pattern_rules_03",
  "status": "active",
  "version": 1,
  "summary": "Symptom icons: circular green-tinted; label below in navy #262262 (tok_ibsrela_color_dark_blue)."
}