{
  "id": "rule_ibsrela_purple_reserved_for_title_first_line",
  "brand_id": "ibsrela",
  "rule_class": "color_application",
  "scope": "org_baseline",
  "selector": {
    "element_path": "title.color"
  },
  "evaluation_scope": "email",
  "constraint_type": "exclusivity",
  "effect": {
    "subject": "Purple #92278F text",
    "reserved_for": "title / first line of the email only"
  },
  "polarity": "must",
  "hardness": "hard_constraint",
  "precedence": 0,
  "token_ids": [],
  "asset_ids": [],
  "governance_ids": [
    "gov_ibsrela_title_purple_only"
  ],
  "rule_text": "Title is how the email starts and should always be purple; the first line in the email should always be purple. No other text in the email may be purple colored.",
  "intent": "Reserve purple as the distinctive opening text color.",
  "source": "design_bible",
  "doc_ref": "color_scheme_rules[0]",
  "group_id": "grp_ibsrela_color_scheme_rules_00",
  "status": "active",
  "version": 1,
  "summary": "Title and first email line must be purple; no other text in the email may use purple."
}